{
  "AIName": "Monster_AML_Elite01_01",
  "VariableList": [
    {
      "$type": "RPG.GameCore.AIVariableString",
      "Value": "RO_015_Phase01",
      "Name": "CurrentPhase"
    },
    {
      "$type": "RPG.GameCore.AIVariableBool",
      "Value": true,
      "Name": "ForbidClearSkillUseRecord"
    }
  ],
  "DecisionList": [
    {
      "$type": "RPG.GameCore.AIDecisionConfig",
      "DecisionName": "UseSkill03",
      "ScoreEvaluatorType": "DefaultDSE",
      "Weight": {
        "Value": 0.499999992619036
      },
      "ConsiderAxisList": [
        {
          "$type": "RPG.GameCore.CheckPredicateAxis",
          "Predicate": {
            "$type": "RPG.GameCore.ByAnd",
            "PredicateList": [
              {
                "$type": "RPG.GameCore.ByCompareDynamicValue",
                "TargetType": {
                  "$type": "RPG.GameCore.TargetAlias",
                  "Alias": "Caster"
                },
                "DynamicKey": "Monster_AML_Elite01_01_AICounter_01",
                "ContextScope": "TargetEntity",
                "CompareType": "Equal",
                "CompareValue": {
                  "IsDynamic": false,
                  "FixedValue": {
                    "Value": 2.9999999529202483
                  }
                }
              },
              {
                "$type": "RPG.GameCore.ByCompareDynamicValue",
                "TargetType": {
                  "$type": "RPG.GameCore.TargetAlias",
                  "Alias": "Caster"
                },
                "DynamicKey": "Monster_AML_Elite01_01_AICounter_02",
                "ContextScope": "TargetEntity",
                "CompareType": "Equal",
                "CompareValue": {
                  "IsDynamic": false,
                  "FixedValue": {
                    "Value": 0.9999999843067494
                  }
                }
              }
            ]
          },
          "SuccessScore": {
            "Value": 0.499999992619036
          }
        }
      ],
      "RootTask": {
        "$type": "RPG.GameCore.SequenceConfig",
        "TaskList": [
          {
            "$type": "RPG.GameCore.DefineDynamicValue",
            "TargetType": {
              "$type": "RPG.GameCore.TargetAlias",
              "Alias": "Caster"
            },
            "DynamicKey": "Monster_AML_Elite01_01_AICounter_01",
            "ResetValue": {
              "IsDynamic": false,
              "FixedValue": {
                "Value": 3.9999999372269976
              }
            },
            "ContextScope": "TargetEntity"
          },
          {
            "$type": "RPG.GameCore.DefineDynamicValue",
            "TargetType": {
              "$type": "RPG.GameCore.TargetAlias",
              "Alias": "Caster"
            },
            "DynamicKey": "Monster_AML_Elite01_01_AICounter_02",
            "ResetValue": {
              "IsDynamic": false,
              "FixedValue": {
                "Value": 0.9999999843067494
              }
            },
            "ContextScope": "TargetEntity"
          },
          {
            "$type": "RPG.GameCore.SelectAISkillTarget",
            "SkillName": "Skill03",
            "Selector": {
              "$type": "RPG.GameCore.AIModifierNameSelector",
              "ModifierName": "MCommon_DOT_Poison",
              "InverseResultFlag": true
            }
          },
          {
            "$type": "RPG.GameCore.UseSkill",
            "SkillName": "Skill03"
          }
        ]
      }
    },
    {
      "$type": "RPG.GameCore.AIDecisionConfig",
      "DecisionName": "UseSkill04",
      "ScoreEvaluatorType": "DefaultDSE",
      "Weight": {
        "Value": 0.8999999867142647
      },
      "ConsiderAxisList": [
        {
          "$type": "RPG.GameCore.CheckPredicateAxis",
          "Predicate": {
            "$type": "RPG.GameCore.ByAnd",
            "PredicateList": [
              {
                "$type": "RPG.GameCore.ByCompareDynamicValue",
                "TargetType": {
                  "$type": "RPG.GameCore.TargetAlias",
                  "Alias": "Caster"
                },
                "DynamicKey": "Monster_AML_Elite01_01_AICounter_01",
                "ContextScope": "TargetEntity",
                "CompareType": "Equal",
                "CompareValue": {
                  "IsDynamic": false,
                  "FixedValue": {
                    "Value": 3.9999999372269976
                  }
                }
              },
              {
                "$type": "RPG.GameCore.ByCompareDynamicValue",
                "TargetType": {
                  "$type": "RPG.GameCore.TargetAlias",
                  "Alias": "Caster"
                },
                "DynamicKey": "Monster_AML_Elite01_01_AICounter_02",
                "ContextScope": "TargetEntity",
                "CompareType": "Equal",
                "CompareValue": {
                  "IsDynamic": false,
                  "FixedValue": {
                    "Value": 0.9999999843067494
                  }
                }
              }
            ]
          },
          "SuccessScore": {
            "Value": 0.499999992619036
          }
        }
      ],
      "RootTask": {
        "$type": "RPG.GameCore.SequenceConfig",
        "TaskList": [
          {
            "$type": "RPG.GameCore.PredicateTaskList",
            "Predicate": {
              "$type": "RPG.GameCore.ByIsContainModifier",
              "TargetType": {
                "$type": "RPG.GameCore.TargetAlias",
                "Alias": "Caster"
              },
              "ModifierName": "OneMore"
            },
            "SuccessTaskList": [
              {
                "$type": "RPG.GameCore.DefineDynamicValue",
                "TargetType": {
                  "$type": "RPG.GameCore.TargetAlias",
                  "Alias": "Caster"
                },
                "DynamicKey": "Monster_AML_Elite01_01_AICounter_01",
                "ResetValue": {
                  "IsDynamic": false,
                  "FixedValue": {
                    "Value": 3.9999999372269976
                  }
                },
                "ContextScope": "TargetEntity"
              },
              {
                "$type": "RPG.GameCore.DefineDynamicValue",
                "TargetType": {
                  "$type": "RPG.GameCore.TargetAlias",
                  "Alias": "Caster"
                },
                "DynamicKey": "Monster_AML_Elite01_01_AICounter_02",
                "ResetValue": {
                  "IsDynamic": false,
                  "FixedValue": {
                    "Value": 0.9999999843067494
                  }
                },
                "ContextScope": "TargetEntity"
              },
              {
                "$type": "RPG.GameCore.UseSkill",
                "SkillName": "Skill03"
              }
            ],
            "FailedTaskList": [
              {
                "$type": "RPG.GameCore.DefineDynamicValue",
                "TargetType": {
                  "$type": "RPG.GameCore.TargetAlias",
                  "Alias": "Caster"
                },
                "DynamicKey": "Monster_AML_Elite01_01_AICounter_01",
                "ResetValue": {
                  "IsDynamic": false,
                  "FixedValue": {
                    "Value": 4.999999921533747
                  }
                },
                "ContextScope": "TargetEntity"
              },
              {
                "$type": "RPG.GameCore.DefineDynamicValue",
                "TargetType": {
                  "$type": "RPG.GameCore.TargetAlias",
                  "Alias": "Caster"
                },
                "DynamicKey": "Monster_AML_Elite01_01_AICounter_02",
                "ResetValue": {
                  "IsDynamic": false,
                  "FixedValue": {
                    "Value": 1.9999999686134988
                  }
                },
                "ContextScope": "TargetEntity"
              },
              {
                "$type": "RPG.GameCore.UseSkill",
                "SkillName": "Skill04"
              }
            ]
          }
        ]
      }
    },
    {
      "$type": "RPG.GameCore.AIDecisionConfig",
      "DecisionName": "UseSkill05",
      "ScoreEvaluatorType": "DefaultDSE",
      "Weight": {
        "Value": 0.499999992619036
      },
      "ConsiderAxisList": [
        {
          "$type": "RPG.GameCore.CheckPredicateAxis",
          "Predicate": {
            "$type": "RPG.GameCore.ByAnd",
            "PredicateList": [
              {
                "$type": "RPG.GameCore.ByCompareDynamicValue",
                "TargetType": {
                  "$type": "RPG.GameCore.TargetAlias",
                  "Alias": "Caster"
                },
                "DynamicKey": "Monster_AML_Elite01_01_AICounter_01",
                "ContextScope": "TargetEntity",
                "CompareType": "Equal",
                "CompareValue": {
                  "IsDynamic": false,
                  "FixedValue": {
                    "Value": 4.999999921533747
                  }
                }
              },
              {
                "$type": "RPG.GameCore.ByCompareDynamicValue",
                "TargetType": {
                  "$type": "RPG.GameCore.TargetAlias",
                  "Alias": "Caster"
                },
                "DynamicKey": "Monster_AML_Elite01_01_AICounter_02",
                "ContextScope": "TargetEntity",
                "CompareType": "Equal",
                "CompareValue": {
                  "IsDynamic": false,
                  "FixedValue": {
                    "Value": 1.9999999686134988
                  }
                }
              }
            ]
          },
          "SuccessScore": {
            "Value": 0.499999992619036
          }
        }
      ],
      "RootTask": {
        "$type": "RPG.GameCore.SequenceConfig",
        "TaskList": [
          {
            "$type": "RPG.GameCore.DefineDynamicValue",
            "TargetType": {
              "$type": "RPG.GameCore.TargetAlias",
              "Alias": "Caster"
            },
            "DynamicKey": "Monster_AML_Elite01_01_AICounter_01",
            "ResetValue": {
              "IsDynamic": false,
              "FixedValue": {
                "Value": 0.9999999843067494
              }
            },
            "ContextScope": "TargetEntity"
          },
          {
            "$type": "RPG.GameCore.DefineDynamicValue",
            "TargetType": {
              "$type": "RPG.GameCore.TargetAlias",
              "Alias": "Caster"
            },
            "DynamicKey": "Monster_AML_Elite01_01_AICounter_02",
            "ResetValue": {
              "IsDynamic": false,
              "FixedValue": {
                "Value": 2.9999999529202483
              }
            },
            "ContextScope": "TargetEntity"
          },
          {
            "$type": "RPG.GameCore.PredicateTaskList",
            "Predicate": {
              "$type": "RPG.GameCore.ByCompareCharacterNumber",
              "TargetType": {
                "$type": "RPG.GameCore.TargetAlias",
                "Alias": "AllLightTeam"
              },
              "Predicate": {
                "$type": "RPG.GameCore.ByIsContainModifier",
                "TargetType": {
                  "$type": "RPG.GameCore.TargetAlias",
                  "Alias": "ParamEntity"
                },
                "ModifierName": "MMonster_AML_Elite01_01_DOTAim"
              },
              "CompareType": "GreaterEqual",
              "CompareNumber": {
                "IsDynamic": false,
                "FixedValue": {
                  "Value": 0.9999999843067494
                }
              }
            },
            "SuccessTaskList": [
              {
                "$type": "RPG.GameCore.UseSkill",
                "SkillName": "Skill05"
              }
            ],
            "FailedTaskList": [
              {
                "$type": "RPG.GameCore.UseSkill",
                "SkillName": "Skill06"
              }
            ]
          }
        ]
      }
    },
    {
      "$type": "RPG.GameCore.AIDecisionConfig",
      "DecisionName": "UseSkill01",
      "ScoreEvaluatorType": "DefaultDSE",
      "Weight": {
        "Value": 0.8999999867142647
      },
      "ConsiderAxisList": [
        {
          "$type": "RPG.GameCore.CheckPredicateAxis",
          "Predicate": {
            "$type": "RPG.GameCore.ByAnd",
            "PredicateList": [
              {
                "$type": "RPG.GameCore.ByCompareDynamicValue",
                "TargetType": {
                  "$type": "RPG.GameCore.TargetAlias",
                  "Alias": "Caster"
                },
                "DynamicKey": "Monster_AML_Elite01_01_AICounter_01",
                "ContextScope": "TargetEntity",
                "CompareType": "Equal",
                "CompareValue": {
                  "IsDynamic": false,
                  "FixedValue": {
                    "Value": 0.9999999843067494
                  }
                }
              },
              {
                "$type": "RPG.GameCore.ByCompareDynamicValue",
                "TargetType": {
                  "$type": "RPG.GameCore.TargetAlias",
                  "Alias": "Caster"
                },
                "DynamicKey": "Monster_AML_Elite01_01_AICounter_02",
                "ContextScope": "TargetEntity",
                "CompareType": "Equal",
                "CompareValue": {
                  "IsDynamic": false,
                  "FixedValue": {
                    "Value": 2.9999999529202483
                  }
                }
              }
            ]
          },
          "SuccessScore": {
            "Value": 0.499999992619036
          }
        }
      ],
      "RootTask": {
        "$type": "RPG.GameCore.SequenceConfig",
        "TaskList": [
          {
            "$type": "RPG.GameCore.DefineDynamicValue",
            "TargetType": {
              "$type": "RPG.GameCore.TargetAlias",
              "Alias": "Caster"
            },
            "DynamicKey": "Monster_AML_Elite01_01_AICounter_01",
            "ResetValue": {
              "IsDynamic": false,
              "FixedValue": {
                "Value": 2.9999999529202483
              }
            },
            "ContextScope": "TargetEntity"
          },
          {
            "$type": "RPG.GameCore.DefineDynamicValue",
            "TargetType": {
              "$type": "RPG.GameCore.TargetAlias",
              "Alias": "Caster"
            },
            "DynamicKey": "Monster_AML_Elite01_01_AICounter_02",
            "ResetValue": {
              "IsDynamic": false,
              "FixedValue": {
                "Value": 0.9999999843067494
              }
            },
            "ContextScope": "TargetEntity"
          },
          {
            "$type": "RPG.GameCore.PredicateTaskList",
            "Predicate": {
              "$type": "RPG.GameCore.ByCompareCharacterNumber",
              "TargetType": {
                "$type": "RPG.GameCore.TargetAlias",
                "Alias": "CasterSummonedMinions"
              },
              "CompareType": "LessEqual",
              "CompareNumber": {
                "IsDynamic": false,
                "FixedValue": {
                  "Value": 1.9999999686134988
                }
              }
            },
            "SuccessTaskList": [
              {
                "$type": "RPG.GameCore.UseSkill",
                "SkillName": "Skill09"
              }
            ],
            "FailedTaskList": [
              {
                "$type": "RPG.GameCore.UseSkill",
                "SkillName": "Skill09"
              }
            ]
          }
        ]
      }
    }
  ]
}